{
    "dynamic": false,
    "elements": {
        "class": {
            "properties": [
                {
                    "readonly": true,
                    "value": "1",
                    "array": false,
                    "name": "ROUND",
                    "description": "Round.",
                    "type": "int"
                },
                {
                    "readonly": true,
                    "value": "2",
                    "array": false,
                    "name": "DIAMOND",
                    "description": "Diamond.",
                    "type": "int"
                },
                {
                    "readonly": true,
                    "value": "3",
                    "array": false,
                    "name": "ELLIPSE",
                    "description": "Ellipse.",
                    "type": "int"
                },
                {
                    "readonly": true,
                    "value": "4",
                    "array": false,
                    "name": "LINE",
                    "description": "Line.",
                    "type": "int"
                },
                {
                    "readonly": true,
                    "value": "5",
                    "array": false,
                    "name": "SQUARE",
                    "description": "Square.",
                    "type": "int"
                },
                {
                    "readonly": true,
                    "value": "6",
                    "array": false,
                    "name": "CROSS",
                    "description": "Cross.",
                    "type": "int"
                }
            ]
        },
        "instance": {
            "methods": [],
            "properties": []
        }
    },
    "name": "BitmapHalfToneType",
    "description": "The shape of the dots (ink deposits) in the halftone screen."
}