{
  "name": "CropToType",
  "enumeration": true,
  "shortdesc": "The style to use when cropping a page.",
  "elements": [
    {
      "type": "class",
      "property": [
        {
          "name": "BOUNDINGBOX",
          "rwaccess": "readonly",
          "shortdesc": "Crop to the bounding box.",
          "datatype": {
            "type": "int",
            "value": 0
          }
        },
        {
          "name": "MEDIABOX",
          "rwaccess": "readonly",
          "shortdesc": "Crop to the media box.",
          "datatype": {
            "type": "int",
            "value": 1
          }
        },
        {
          "name": "CROPBOX",
          "rwaccess": "readonly",
          "shortdesc": "Crop to the crop box.",
          "datatype": {
            "type": "int",
            "value": 2
          }
        },
        {
          "name": "BLEEDBOX",
          "rwaccess": "readonly",
          "shortdesc": "Crop to the bleed box.",
          "datatype": {
            "type": "int",
            "value": 3
          }
        },
        {
          "name": "TRIMBOX",
          "rwaccess": "readonly",
          "shortdesc": "Crop to the trim box.",
          "datatype": {
            "type": "int",
            "value": 4
          }
        },
        {
          "name": "ARTBOX",
          "rwaccess": "readonly",
          "shortdesc": "Crop to the art box.",
          "datatype": {
            "type": "int",
            "value": 5
          }
        }
      ]
    }
  ]
}