{
    "dynamic": false,
    "elements": {
        "class": {
            "properties": [
                {
                    "readonly": true,
                    "value": "1",
                    "array": false,
                    "name": "NONE",
                    "description": "No grid is displayed.",
                    "type": "int"
                },
                {
                    "readonly": true,
                    "value": "2",
                    "array": false,
                    "name": "SMALL",
                    "description": "Small grid squares.",
                    "type": "int"
                },
                {
                    "readonly": true,
                    "value": "3",
                    "array": false,
                    "name": "MEDIUM",
                    "description": "Medium grid squares.",
                    "type": "int"
                },
                {
                    "readonly": true,
                    "value": "4",
                    "array": false,
                    "name": "LARGE",
                    "description": "Large grid squares.",
                    "type": "int"
                }
            ]
        },
        "instance": {
            "methods": [],
            "properties": []
        }
    },
    "name": "GridSize",
    "description": "The size of grid squares."
}