{
    "name": "OpenDocumentType",
    "dynamic": false,
    "elements": {
        "instance": {
            "properties": [],
            "methods": []
        },
        "class": {
            "properties": [
                {
                    "description": "Photoshop format.",
                    "array": false,
                    "readonly": true,
                    "name": "PHOTOSHOP",
                    "value": "1",
                    "type": "int"
                },
                {
                    "description": "BMP format.",
                    "array": false,
                    "readonly": true,
                    "name": "BMP",
                    "value": "2",
                    "type": "int"
                },
                {
                    "description": "CompuServe GIF format.",
                    "array": false,
                    "readonly": true,
                    "name": "COMPUSERVEGIF",
                    "value": "3",
                    "type": "int"
                },
                {
                    "description": "EPS document produced by Photoshop.",
                    "array": false,
                    "readonly": true,
                    "name": "PHOTOSHOPEPS",
                    "value": "4",
                    "type": "int"
                },
                {
                    "description": "Filmstrip format.",
                    "array": false,
                    "readonly": true,
                    "name": "FILMSTRIP",
                    "value": "5",
                    "type": "int"
                },
                {
                    "description": "JPEG format.",
                    "array": false,
                    "readonly": true,
                    "name": "JPEG",
                    "value": "6",
                    "type": "int"
                },
                {
                    "description": "PCX format.",
                    "array": false,
                    "readonly": true,
                    "name": "PCX",
                    "value": "7",
                    "type": "int"
                },
                {
                    "description": "PDF document produced by Photoshop.",
                    "array": false,
                    "readonly": true,
                    "name": "PHOTOSHOPPDF",
                    "value": "8",
                    "type": "int"
                },
                {
                    "description": "Photo CD format.",
                    "array": false,
                    "readonly": true,
                    "name": "PHOTOCD",
                    "value": "9",
                    "type": "int"
                },
                {
                    "description": "PICT file format.",
                    "array": false,
                    "readonly": true,
                    "name": "PICTFILEFORMAT",
                    "value": "10",
                    "type": "int"
                },
                {
                    "description": "PICT resource format.",
                    "array": false,
                    "readonly": true,
                    "name": "PICTRESOURCEFORMAT",
                    "value": "11",
                    "type": "int"
                },
                {
                    "description": "Pixar format.",
                    "array": false,
                    "readonly": true,
                    "name": "PIXAR",
                    "value": "12",
                    "type": "int"
                },
                {
                    "description": "PNG format.",
                    "array": false,
                    "readonly": true,
                    "name": "PNG",
                    "value": "13",
                    "type": "int"
                },
                {
                    "description": "Raw format.",
                    "array": false,
                    "readonly": true,
                    "name": "RAW",
                    "value": "14",
                    "type": "int"
                },
                {
                    "description": "Scitex CT format.",
                    "array": false,
                    "readonly": true,
                    "name": "SCITEXCT",
                    "value": "15",
                    "type": "int"
                },
                {
                    "description": "Targa format.",
                    "array": false,
                    "readonly": true,
                    "name": "TARGA",
                    "value": "16",
                    "type": "int"
                },
                {
                    "description": "TIFF format.",
                    "array": false,
                    "readonly": true,
                    "name": "TIFF",
                    "value": "17",
                    "type": "int"
                },
                {
                    "description": "Photoshop DCS 1.0 format.",
                    "array": false,
                    "readonly": true,
                    "name": "PHOTOSHOPDCS_1",
                    "value": "18",
                    "type": "int"
                },
                {
                    "description": "Photoshop DCS 2.0 format.",
                    "array": false,
                    "readonly": true,
                    "name": "PHOTOSHOPDCS_2",
                    "value": "19",
                    "type": "int"
                },
                {
                    "description": "Generic PDF format.",
                    "array": false,
                    "readonly": true,
                    "name": "PDF",
                    "value": "21",
                    "type": "int"
                },
                {
                    "description": "Generic EPS format.",
                    "array": false,
                    "readonly": true,
                    "name": "EPS",
                    "value": "22",
                    "type": "int"
                },
                {
                    "description": "EPS format with embedded PICT Preview.",
                    "array": false,
                    "readonly": true,
                    "name": "EPSPICTPREVIEW",
                    "value": "23",
                    "type": "int"
                },
                {
                    "description": "EPS format with embedded TIFF Preview.",
                    "array": false,
                    "readonly": true,
                    "name": "EPSTIFFPREVIEW",
                    "value": "24",
                    "type": "int"
                },
                {
                    "description": "Alias PIX format.",
                    "array": false,
                    "readonly": true,
                    "name": "ALIASPIX",
                    "value": "25",
                    "type": "int"
                },
                {
                    "description": "Electric format.",
                    "array": false,
                    "readonly": true,
                    "name": "ELECTRICIMAGE",
                    "value": "26",
                    "type": "int"
                },
                {
                    "description": "Portable Bitmap format.",
                    "array": false,
                    "readonly": true,
                    "name": "PORTABLEBITMAP",
                    "value": "27",
                    "type": "int"
                },
                {
                    "description": "Wavefront RLA format.",
                    "array": false,
                    "readonly": true,
                    "name": "WAVEFRONTRLA",
                    "value": "28",
                    "type": "int"
                },
                {
                    "description": "SGI RGB format.",
                    "array": false,
                    "readonly": true,
                    "name": "SGIRGB",
                    "value": "29",
                    "type": "int"
                },
                {
                    "description": "SoftImage format.",
                    "array": false,
                    "readonly": true,
                    "name": "SOFTIMAGE",
                    "value": "30",
                    "type": "int"
                },
                {
                    "description": "Wireless Bitmap format (WBMP)",
                    "array": false,
                    "readonly": true,
                    "name": "WIRELESSBITMAP",
                    "value": "31",
                    "type": "int"
                },
                {
                    "description": "Camera RAW format.",
                    "array": false,
                    "readonly": true,
                    "name": "CAMERARAW",
                    "value": "32",
                    "type": "int"
                },
                {
                    "description": "DICOM format.",
                    "array": false,
                    "readonly": true,
                    "name": "DICOM",
                    "value": "33",
                    "type": "int"
                }
            ]
        }
    },
    "description": "Document formats that Photoshop can open."
}