{
    "dynamic": false,
    "elements": {
        "class": {
            "properties": [
                {
                    "readonly": true,
                    "value": "1",
                    "array": false,
                    "name": "INSIDE",
                    "description": "The border is placed inside the selection or layer boundaries.",
                    "type": "int"
                },
                {
                    "readonly": true,
                    "value": "2",
                    "array": false,
                    "name": "CENTER",
                    "description": "The border is placed in the center of the the selection or layer boundaries.",
                    "type": "int"
                },
                {
                    "readonly": true,
                    "value": "3",
                    "array": false,
                    "name": "OUTSIDE",
                    "description": "The border is placed outside the selection or layer boundaries.",
                    "type": "int"
                }
            ]
        },
        "instance": {
            "methods": [],
            "properties": []
        }
    },
    "name": "StrokeLocation",
    "description": "The placement of path or selection boundary strokes."
}