{
    "name": "ChangecaseMode",
    "dynamic": false,
    "elements": {
        "class": {
            "properties": [
                {
                    "name": "UPPERCASE",
                    "readonly": true,
                    "type": "Number",
                    "array": false,
                    "description": "Makes all letters uppercase.",
                    "value": "1667462499"
                },
                {
                    "name": "LOWERCASE",
                    "readonly": true,
                    "type": "Number",
                    "array": false,
                    "description": "Makes all letters lowercase.",
                    "value": "1667460195"
                },
                {
                    "name": "TITLECASE",
                    "readonly": true,
                    "type": "Number",
                    "array": false,
                    "description": "Makes the first letter of each word uppercase.",
                    "value": "1667462243"
                },
                {
                    "name": "SENTENCECASE",
                    "readonly": true,
                    "type": "Number",
                    "array": false,
                    "description": "Makes the first letter of each sentence uppercase.",
                    "value": "1667461987"
                }
            ],
            "methods": []
        },
        "constructors": {
            "methods": []
        },
        "instance": {
            "properties": [],
            "methods": []
        }
    },
    "description": "Text case options."
}