{
    "dynamic": true,
    "elements": {
        "class": {
            "properties": []
        },
        "instance": {
            "methods": [
                {
                    "array": false,
                    "parameters": [],
                    "name": "count",
                    "description": "Displays the number of elements in the Ink.",
                    "type": "Number"
                },
                {
                    "array": false,
                    "parameters": [
                        {
                            "optional": false,
                            "array": false,
                            "name": "index",
                            "description": "The index or name. Can accept: Long Integer or String.",
                            "type": "Mixed"
                        }
                    ],
                    "name": "item",
                    "description": "Returns the Ink with the specified index or name.",
                    "type": "Ink"
                },
                {
                    "array": false,
                    "parameters": [
                        {
                            "optional": false,
                            "array": false,
                            "name": "name",
                            "description": "The name.",
                            "type": "String"
                        }
                    ],
                    "name": "itemByName",
                    "description": "Returns the Ink with the specified name.",
                    "type": "Ink"
                },
                {
                    "array": false,
                    "parameters": [
                        {
                            "optional": false,
                            "array": false,
                            "name": "id",
                            "description": "The ID.",
                            "type": "Number"
                        }
                    ],
                    "name": "itemByID",
                    "description": "Returns the Ink with the specified ID.",
                    "type": "Ink"
                },
                {
                    "array": true,
                    "parameters": [
                        {
                            "optional": false,
                            "array": false,
                            "name": "from",
                            "description": "The Ink, index, or name at the beginning of the range. Can accept: Ink, Long Integer or String.",
                            "type": "Mixed"
                        },
                        {
                            "optional": false,
                            "array": false,
                            "name": "to",
                            "description": "The Ink, index, or name at the end of the range. Can accept: Ink, Long Integer or String.",
                            "type": "Mixed"
                        }
                    ],
                    "name": "itemByRange",
                    "description": "Returns the Inks within the specified range.",
                    "type": "Ink"
                },
                {
                    "array": false,
                    "parameters": [],
                    "name": "firstItem",
                    "description": "Returns the first Ink in the collection.",
                    "type": "Ink"
                },
                {
                    "array": false,
                    "parameters": [],
                    "name": "lastItem",
                    "description": "Returns the last Ink in the collection.",
                    "type": "Ink"
                },
                {
                    "array": false,
                    "parameters": [],
                    "name": "middleItem",
                    "description": "Returns the middle Ink in the collection.",
                    "type": "Ink"
                },
                {
                    "array": false,
                    "parameters": [
                        {
                            "optional": false,
                            "array": false,
                            "name": "obj",
                            "description": "The index of the Ink that follows the desired Ink.",
                            "type": "Ink"
                        }
                    ],
                    "name": "previousItem",
                    "description": "Returns the Ink with the index previous to the specified index.",
                    "type": "Ink"
                },
                {
                    "array": false,
                    "parameters": [
                        {
                            "optional": false,
                            "array": false,
                            "name": "obj",
                            "description": "The Ink whose index comes before the desired Ink.",
                            "type": "Ink"
                        }
                    ],
                    "name": "nextItem",
                    "description": "Returns the Ink whose index follows the specified Ink in the collection.",
                    "type": "Ink"
                },
                {
                    "array": false,
                    "parameters": [],
                    "name": "anyItem",
                    "description": "Returns any Ink in the collection.",
                    "type": "Ink"
                },
                {
                    "array": true,
                    "parameters": [],
                    "name": "everyItem",
                    "description": "Returns every Ink in the collection.",
                    "type": "Ink"
                },
                {
                    "array": false,
                    "parameters": [],
                    "name": "toSource",
                    "description": "Generates a string which, if executed, will return the Ink.",
                    "type": "String"
                },
                {
                    "array": false,
                    "parameters": [
                        {
                            "optional": false,
                            "array": false,
                            "name": "index",
                            "description": "The index.",
                            "type": "Number"
                        }
                    ],
                    "name": "[]",
                    "description": "Returns the Ink with the specified index.",
                    "type": "Ink"
                }
            ],
            "properties": [
                {
                    "readonly": true,
                    "array": false,
                    "name": "length",
                    "description": "The number of objects in the collection.",
                    "type": "Number"
                }
            ]
        }
    },
    "name": "Inks",
    "description": "A collection of inks."
}