{
    "name": "TimingTargets",
    "dynamic": true,
    "elements": {
        "class": {
            "properties": [],
            "methods": []
        },
        "constructors": {
            "methods": []
        },
        "instance": {
            "properties": [
                {
                    "name": "length",
                    "readonly": true,
                    "type": "Number",
                    "array": false,
                    "description": "The number of objects in the collection."
                }
            ],
            "methods": [
                {
                    "name": "add",
                    "parameters": [
                        {
                            "name": "dynamicTarget",
                            "type": "Mixed",
                            "array": false,
                            "optional": false,
                            "description": "A page item target that is an animation, media, or mso. Can accept: PageItem, Graphic, Behavior or MediaItem."
                        },
                        {
                            "name": "delaySeconds",
                            "type": "Number",
                            "array": false,
                            "optional": true,
                            "description": "The time delay in seconds for a target. (Optional)",
                            "value": "0"
                        },
                        {
                            "name": "withProperties",
                            "type": "Object",
                            "array": false,
                            "optional": false,
                            "description": "Initial values for properties of the new TimingTarget (Optional)"
                        }
                    ],
                    "description": "Adds a new target item.",
                    "type": "TimingTarget",
                    "array": false
                },
                {
                    "name": "count",
                    "parameters": [],
                    "description": "Displays the number of elements in the TimingTarget.",
                    "type": "Number",
                    "array": false
                },
                {
                    "name": "item",
                    "parameters": [
                        {
                            "name": "index",
                            "type": "Mixed",
                            "array": false,
                            "optional": false,
                            "description": "The index or name. Can accept: Long Integer or String."
                        }
                    ],
                    "description": "Returns the TimingTarget with the specified index or name.",
                    "type": "TimingTarget",
                    "array": false
                },
                {
                    "name": "itemByRange",
                    "parameters": [
                        {
                            "name": "from",
                            "type": "Mixed",
                            "array": false,
                            "optional": false,
                            "description": "The TimingTarget, index, or name at the beginning of the range. Can accept: TimingTarget, Long Integer or String."
                        },
                        {
                            "name": "to",
                            "type": "Mixed",
                            "array": false,
                            "optional": false,
                            "description": "The TimingTarget, index, or name at the end of the range. Can accept: TimingTarget, Long Integer or String."
                        }
                    ],
                    "description": "Returns the TimingTargets within the specified range.",
                    "type": "TimingTarget",
                    "array": true
                },
                {
                    "name": "firstItem",
                    "parameters": [],
                    "description": "Returns the first TimingTarget in the collection.",
                    "type": "TimingTarget",
                    "array": false
                },
                {
                    "name": "lastItem",
                    "parameters": [],
                    "description": "Returns the last TimingTarget in the collection.",
                    "type": "TimingTarget",
                    "array": false
                },
                {
                    "name": "middleItem",
                    "parameters": [],
                    "description": "Returns the middle TimingTarget in the collection.",
                    "type": "TimingTarget",
                    "array": false
                },
                {
                    "name": "previousItem",
                    "parameters": [
                        {
                            "name": "obj",
                            "type": "TimingTarget",
                            "array": false,
                            "optional": false,
                            "description": "The index of the TimingTarget that follows the desired TimingTarget."
                        }
                    ],
                    "description": "Returns the TimingTarget with the index previous to the specified index.",
                    "type": "TimingTarget",
                    "array": false
                },
                {
                    "name": "nextItem",
                    "parameters": [
                        {
                            "name": "obj",
                            "type": "TimingTarget",
                            "array": false,
                            "optional": false,
                            "description": "The TimingTarget whose index comes before the desired TimingTarget."
                        }
                    ],
                    "description": "Returns the TimingTarget whose index follows the specified TimingTarget in the collection.",
                    "type": "TimingTarget",
                    "array": false
                },
                {
                    "name": "anyItem",
                    "parameters": [],
                    "description": "Returns any TimingTarget in the collection.",
                    "type": "TimingTarget",
                    "array": false
                },
                {
                    "name": "everyItem",
                    "parameters": [],
                    "description": "Returns every TimingTarget in the collection.",
                    "type": "TimingTarget",
                    "array": true
                },
                {
                    "name": "toSource",
                    "parameters": [],
                    "description": "Generates a string which, if executed, will return the TimingTarget.",
                    "type": "String",
                    "array": false
                },
                {
                    "name": "[]",
                    "parameters": [
                        {
                            "name": "index",
                            "type": "Number",
                            "array": false,
                            "optional": false,
                            "description": "The index."
                        }
                    ],
                    "description": "Returns the TimingTarget with the specified index.",
                    "type": "TimingTarget",
                    "array": false
                }
            ]
        }
    },
    "description": "A collection of timing target."
}