{
    "name": "ColorReductionMethod",
    "dynamic": false,
    "elements": {
        "instance": {
            "properties": [],
            "methods": []
        },
        "class": {
            "properties": [
                {
                    "name": "SELECTIVE",
                    "array": false,
                    "value": "0x536C7476",
                    "type": "int",
                    "readonly": true
                },
                {
                    "name": "ADAPTIVE",
                    "array": false,
                    "value": "0x41647074",
                    "type": "int",
                    "readonly": true
                },
                {
                    "name": "PERCEPTUAL",
                    "array": false,
                    "value": "0x50726370",
                    "type": "int",
                    "readonly": true
                },
                {
                    "name": "WEB",
                    "array": false,
                    "value": "0x57656220",
                    "type": "int",
                    "readonly": true
                }
            ]
        }
    },
    "description": "Method used to reduce color for PNG8 and GIF export formats."
}