{
    "name": "ExportOptionsPNG24",
    "dynamic": true,
    "elements": {
        "class": {
            "properties": [
                {
                    "name": "transparency",
                    "readonly": false,
                    "type": "Boolean",
                    "array": false,
                    "description": "Should the resulting image use transparency.",
                    "value": "true"
                },
                {
                    "name": "matte",
                    "readonly": false,
                    "type": "Boolean",
                    "array": false,
                    "description": "Should the artboard be matted with a color.",
                    "value": "true"
                },
                {
                    "name": "matteColor",
                    "readonly": false,
                    "type": "RGBColor",
                    "array": false,
                    "description": "The color to use when matting the artboard (default: white)"
                },
                {
                    "name": "horizontalScale",
                    "readonly": false,
                    "type": "Number",
                    "array": false,
                    "description": "Horizontal scaling factor.",
                    "value": "100"
                },
                {
                    "name": "verticalScale",
                    "readonly": false,
                    "type": "Number",
                    "array": false,
                    "description": "Vertical scaling factor.",
                    "value": "100"
                },
                {
                    "name": "antiAliasing",
                    "readonly": false,
                    "type": "Boolean",
                    "array": false,
                    "description": "Should the resulting image be antialiased.",
                    "value": "true"
                },
                {
                    "name": "artBoardClipping",
                    "readonly": false,
                    "type": "Boolean",
                    "array": false,
                    "description": "Should the resulting image be clipped to the artboard.",
                    "value": "false"
                },
                {
                    "name": "saveAsHTML",
                    "readonly": false,
                    "type": "Boolean",
                    "array": false,
                    "description": "Should the resulting image be saved as HTML.",
                    "value": "false"
                },
                {
                    "name": "dimensions",
                    "readonly": false,
                    "type": "Dimensions",
                    "array": false,
                    "description": "Dimensions in which to contain the resulting raster."
                }
            ],
            "methods": []
        },
        "constructors": {
            "methods": []
        },
        "instance": {
            "properties": [],
            "methods": []
        }
    },
    "description": "Options which may be supplied when exporting a document as an 24 bit PNG file."
}