{
    "name": "FXGVersion",
    "dynamic": false,
    "elements": {
        "instance": {
            "properties": [],
            "methods": []
        },
        "class": {
            "properties": [
                {
                    "description": "FXG version 1.0.",
                    "array": false,
                    "readonly": true,
                    "name": "VERSION1PT0",
                    "value": "1",
                    "type": "int"
                },
                {
                    "description": "FXG version 2.0.",
                    "array": false,
                    "readonly": true,
                    "name": "VERSION2PT0",
                    "value": "2",
                    "type": "int"
                }
            ]
        }
    },
    "description": "The FXG file format version."
}