{
    "name": "GradientsPreservePolicy",
    "dynamic": false,
    "elements": {
        "instance": {
            "properties": [],
            "methods": []
        },
        "class": {
            "properties": [
                {
                    "description": "Preserve the editability of gradients.",
                    "array": false,
                    "readonly": true,
                    "name": "KEEPGRADIENTSEDITABLE",
                    "value": "3",
                    "type": "int"
                },
                {
                    "description": "Automatically Convert Gradients.",
                    "array": false,
                    "readonly": true,
                    "name": "AUTOMATICALLYCONVERTGRADIENTS",
                    "value": "4",
                    "type": "int"
                }
            ]
        }
    },
    "description": "Gradients preserve policy used by FXG file format."
}