{
    "name": "PerspectiveGridPlaneType",
    "dynamic": false,
    "elements": {
        "instance": {
            "properties": [],
            "methods": []
        },
        "class": {
            "properties": [
                {
                    "description": "Invalid Perspective Grid Plane Type.",
                    "array": false,
                    "readonly": true,
                    "name": "NOPLANE",
                    "value": "0",
                    "type": "int"
                },
                {
                    "description": "Perspective Grid Left Plane Type.",
                    "array": false,
                    "readonly": true,
                    "name": "LEFTPLANE",
                    "value": "1",
                    "type": "int"
                },
                {
                    "description": "Perspective Grid Right Plane Type.",
                    "array": false,
                    "readonly": true,
                    "name": "RIGHTPLANE",
                    "value": "2",
                    "type": "int"
                },
                {
                    "description": "Perspective Grid Floor Plane Type.",
                    "array": false,
                    "readonly": true,
                    "name": "FLOORPLANE",
                    "value": "3",
                    "type": "int"
                }
            ]
        }
    },
    "description": "Perspective grid plane types."
}