{
  "name": "TextStyleRanges",
  "dynamic": true,
  "shortdesc": "A collection of text style ranges.",
  "elements": [
    {
      "type": "instance",
      "method": [
        {
          "name": "count",
          "shortdesc": "Displays the number of elements in the TextStyleRange.",
          "datatype": {
            "type": "Number"
          }
        },
        {
          "name": "item",
          "shortdesc": "Returns the TextStyleRange with the specified index or name.",
          "parameters": [
            {
              "name": "index",
              "shortdesc": "The index or name. Can accept: Long Integer or String.",
              "datatype": {
                "type": "Mixed"
              }
            }
          ],
          "datatype": {
            "type": "TextStyleRange"
          }
        },
        {
          "name": "itemByRange",
          "shortdesc": "Returns the TextStyleRanges within the specified range.",
          "parameters": [
            {
              "name": "from",
              "shortdesc": "The TextStyleRange, index, or name at the beginning of the range. Can accept: TextStyleRange, Long Integer or String.",
              "datatype": {
                "type": "Mixed"
              }
            },
            {
              "name": "to",
              "shortdesc": "The TextStyleRange, index, or name at the end of the range. Can accept: TextStyleRange, Long Integer or String.",
              "datatype": {
                "type": "Mixed"
              }
            }
          ],
          "datatype": {
            "type": "TextStyleRange",
            "array": true
          }
        },
        {
          "name": "firstItem",
          "shortdesc": "Returns the first TextStyleRange in the collection.",
          "datatype": {
            "type": "TextStyleRange"
          }
        },
        {
          "name": "lastItem",
          "shortdesc": "Returns the last TextStyleRange in the collection.",
          "datatype": {
            "type": "TextStyleRange"
          }
        },
        {
          "name": "middleItem",
          "shortdesc": "Returns the middle TextStyleRange in the collection.",
          "datatype": {
            "type": "TextStyleRange"
          }
        },
        {
          "name": "previousItem",
          "shortdesc": "Returns the TextStyleRange with the index previous to the specified index.",
          "parameters": [
            {
              "name": "obj",
              "shortdesc": "The index of the TextStyleRange that follows the desired TextStyleRange.",
              "datatype": {
                "type": "TextStyleRange"
              }
            }
          ],
          "datatype": {
            "type": "TextStyleRange"
          }
        },
        {
          "name": "nextItem",
          "shortdesc": "Returns the TextStyleRange whose index follows the specified TextStyleRange in the collection.",
          "parameters": [
            {
              "name": "obj",
              "shortdesc": "The TextStyleRange whose index comes before the desired TextStyleRange.",
              "datatype": {
                "type": "TextStyleRange"
              }
            }
          ],
          "datatype": {
            "type": "TextStyleRange"
          }
        },
        {
          "name": "anyItem",
          "shortdesc": "Returns any TextStyleRange in the collection.",
          "datatype": {
            "type": "TextStyleRange"
          }
        },
        {
          "name": "everyItem",
          "shortdesc": "Returns every TextStyleRange in the collection.",
          "datatype": {
            "type": "TextStyleRange",
            "array": true
          }
        },
        {
          "name": "toSource",
          "shortdesc": "Generates a string which, if executed, will return the TextStyleRange.",
          "datatype": {
            "type": "String"
          }
        },
        {
          "name": "[]",
          "shortdesc": "Returns the TextStyleRange with the specified index.",
          "parameters": [
            {
              "name": "index",
              "shortdesc": "The index.",
              "datatype": {
                "type": "Number"
              }
            }
          ],
          "datatype": {
            "type": "TextStyleRange"
          }
        }
      ],
      "property": [
        {
          "name": "length",
          "rwaccess": "readonly",
          "shortdesc": "The number of objects in the collection.",
          "datatype": {
            "type": "Number"
          }
        }
      ]
    }
  ]
}